qdl.cpython-38-x86_64-linux-gnu.so
qdl.libs/libxml2-e04a0072.so.2.7.6
qdl.libs/libz-eb09ad1d.so.1.2.3
qdl.libs/libusb-1-e58f329c.0.so.0.1.0
qdl-1.2.0.dist-info/LICENSE
qdl-1.2.0.dist-info/METADATA
qdl-1.2.0.dist-info/top_level.txt
qdl-1.2.0.dist-info/RECORD
qdl-1.2.0.dist-info/WHEEL
