Metadata-Version: 2.1
Name: qdl
Version: 1.2.0
Summary: QDL C wrapper
Home-page: UNKNOWN
Author: UNKNOWN
Author-email: UNKNOWN
License: UNKNOWN
Platform: UNKNOWN
